u3driver/__init__.py
u3driver/__version__.py
u3driver/altElement.py
u3driver/altUnityExceptions.py
u3driver/by.py
u3driver/runner.py
u3driver/commands/__init__.py
u3driver/commands/base_command.py
u3driver/commands/call_static_method.py
u3driver/commands/close_connection.py
u3driver/commands/command_returning_alt_elements.py
u3driver/commands/custom_interface.py
u3driver/commands/debug_mode.py
u3driver/commands/enable_logging.py
u3driver/commands/get_constructor.py
u3driver/commands/get_game_version.py
u3driver/commands/get_project_info.py
u3driver/commands/get_server_version.py
u3driver/commands/get_static_method.py
u3driver/commands/get_unity_version.py
u3driver/commands/profiling_memory.py
u3driver/commands/record_profile.py
u3driver/commands/FindObjects/__init__.py
u3driver/commands/FindObjects/find_all_objects.py
u3driver/commands/FindObjects/find_all_objects_where_text_contains.py
u3driver/commands/FindObjects/find_all_text.py
u3driver/commands/FindObjects/find_child.py
u3driver/commands/FindObjects/find_object.py
u3driver/commands/FindObjects/find_object_and_tap.py
u3driver/commands/FindObjects/find_object_in_range_where_name_contains.py
u3driver/commands/FindObjects/find_object_in_range_where_text_contains.py
u3driver/commands/FindObjects/find_object_which_contains.py
u3driver/commands/FindObjects/find_objects_which_contains.py
u3driver/commands/FindObjects/find_text.py
u3driver/commands/FindObjects/get_hierarchy.py
u3driver/commands/FindObjects/get_inspector.py
u3driver/commands/FindObjects/get_object_rect.py
u3driver/commands/FindObjects/get_screen.py
u3driver/commands/FindObjects/get_value_on_component.py
u3driver/commands/FindObjects/object_exist.py
u3driver/commands/InputActions/__init__.py
u3driver/commands/InputActions/tap_at_coordinates.py
u3driver/commands/ObjectCommands/__init__.py
u3driver/commands/ObjectCommands/call_component_method.py
u3driver/commands/ObjectCommands/child_index.py
u3driver/commands/ObjectCommands/drag.py
u3driver-1.0.49.dist-info/METADATA
u3driver-1.0.49.dist-info/WHEEL
u3driver-1.0.49.dist-info/top_level.txt
u3driver-1.0.49.dist-info/RECORD
