Metadata-Version: 2.1
Name: u3driver
Version: 1.0.49
Summary: u3driver
Home-page: https://github.com/king3soft/u3driver
Author: king3soft
Author-email: buutuud@gmail.com
License: GPLv3
Platform: UNKNOWN
Requires-Python: >=3.6
